doit_auto1/__init__.py
doit_auto1/cmd_auto.py
doit_auto1/filewatch.py
doit_auto1-0.1.0.dist-info/AUTHORS
doit_auto1-0.1.0.dist-info/LICENSE
doit_auto1-0.1.0.dist-info/METADATA
doit_auto1-0.1.0.dist-info/WHEEL
doit_auto1-0.1.0.dist-info/entry_points.txt
doit_auto1-0.1.0.dist-info/top_level.txt
doit_auto1-0.1.0.dist-info/RECORD
